EventNotifier/Notifier.py
EventNotifier/SubscriberManager.py
EventNotifier/__init__.py
event_notifier-1.0.13.dist-info/LICENSE
event_notifier-1.0.13.dist-info/METADATA
event_notifier-1.0.13.dist-info/WHEEL
event_notifier-1.0.13.dist-info/top_level.txt
event_notifier-1.0.13.dist-info/RECORD
