Metadata-Version: 2.1
Name: event-notifier
Version: 1.0.13
Summary: Event notifier with many subscribers support
Home-page: https://github.com/vitalij555/event-notifier
Author: Vitalij Gotovskij
Author-email: vitalij@cdeveloper.eu
License: MIT
Keywords: EVENT,NOTIFY,SUBSCRIBE,OBSERVER
Classifier: Development Status :: 5 - Production/Stable
Classifier: Intended Audience :: Developers
Classifier: Topic :: Software Development :: Build Tools
Classifier: Operating System :: OS Independent
Classifier: License :: OSI Approved :: MIT License
Classifier: Programming Language :: Python :: 3
Classifier: Programming Language :: Python :: 3.4
Classifier: Programming Language :: Python :: 3.5
Classifier: Programming Language :: Python :: 3.6
Classifier: Programming Language :: Python :: 3.7
Classifier: Programming Language :: Python :: 3.8
Classifier: Programming Language :: Python :: 3.9
Classifier: Programming Language :: Python :: 3.10
Classifier: Programming Language :: Python :: 3.11
License-File: LICENSE
